example/__init__.py
example/main.py
example/custom_management/__init__.py
example/custom_management/customConfig.py
example/custom_management/customConfigManager.py
example/custom_management/customExpConfig.py
example/custom_management/customExpResults.py
example/custom_management/customExperiment.py
example/custom_management/customExtraConfig.py
example/custom_management/customHyperparams.py
example/custom_management/customResultsManager.py
experiments_manager/__init__.py
experiments_manager/paths.py
experiments_manager/config/__init__.py
experiments_manager/config/config.py
experiments_manager/config/configManager.py
experiments_manager/config/configResult.py
experiments_manager/config/expConfig.py
experiments_manager/config/extraConfig.py
experiments_manager/config/hyperparams.py
experiments_manager/experiment/__init__.py
experiments_manager/experiment/experiment.py
experiments_manager/experiment/experimentManager.py
experiments_manager/results/__init__.py
experiments_manager/results/expResults.py
experiments_manager/results/resultsManager.py
experiments_manager/utils/__init__.py
experiments_manager/utils/utils_dict.py
experiments_manager/utils/utils_files.py
experiments_manager/utils/utils_others.py
experiments_manager-0.1.dist-info/METADATA
experiments_manager-0.1.dist-info/WHEEL
experiments_manager-0.1.dist-info/top_level.txt
experiments_manager-0.1.dist-info/RECORD
